image_text_reader/__init__.py
image_text_reader/image_text_reader.py
image_text_reader-1.0.1.dist-info/LICENSE
image_text_reader-1.0.1.dist-info/METADATA
image_text_reader-1.0.1.dist-info/WHEEL
image_text_reader-1.0.1.dist-info/top_level.txt
image_text_reader-1.0.1.dist-info/RECORD
